st_on_hover_tabs_venrup/__init__.py
st_on_hover_tabs_venrup/frontend/build/asset-manifest.json
st_on_hover_tabs_venrup/frontend/build/bootstrap.min.css
st_on_hover_tabs_venrup/frontend/build/index.html
st_on_hover_tabs_venrup/frontend/build/precache-manifest.f1f7fb238023ea049f706bacb01f2dbe.js
st_on_hover_tabs_venrup/frontend/build/service-worker.js
st_on_hover_tabs_venrup/frontend/build/static/css/2.0a4cb73c.chunk.css
st_on_hover_tabs_venrup/frontend/build/static/css/2.0a4cb73c.chunk.css.map
st_on_hover_tabs_venrup/frontend/build/static/css/main.db61388b.chunk.css
st_on_hover_tabs_venrup/frontend/build/static/css/main.db61388b.chunk.css.map
st_on_hover_tabs_venrup/frontend/build/static/js/2.45f23a6f.chunk.js
st_on_hover_tabs_venrup/frontend/build/static/js/2.45f23a6f.chunk.js.LICENSE.txt
st_on_hover_tabs_venrup/frontend/build/static/js/2.45f23a6f.chunk.js.map
st_on_hover_tabs_venrup/frontend/build/static/js/main.e4acf009.chunk.js
st_on_hover_tabs_venrup/frontend/build/static/js/main.e4acf009.chunk.js.map
st_on_hover_tabs_venrup/frontend/build/static/js/runtime-main.11ec9aca.js
st_on_hover_tabs_venrup/frontend/build/static/js/runtime-main.11ec9aca.js.map
streamlit_on_Hover_tabs_venrup-2.0.3.dist-info/LICENSE
streamlit_on_Hover_tabs_venrup-2.0.3.dist-info/METADATA
streamlit_on_Hover_tabs_venrup-2.0.3.dist-info/WHEEL
streamlit_on_Hover_tabs_venrup-2.0.3.dist-info/top_level.txt
streamlit_on_Hover_tabs_venrup-2.0.3.dist-info/RECORD
